<?xml version="1.0" encoding="UTF-8"?>
<objects serializationModel="Studio.02.02.00">
	<object class="EncodingSetting" id="{6f1412aa-4f03-43bc-a45f-38de82d545ba}">
		<property name="encodingFormat">
			<value>3</value>
		</property>
		<property name="quality">
			<value>37</value>
		</property>
		<relationship name="platform">
			<destination>{a4fc7b1b-313e-4c89-825b-d23ece5fbcc3}</destination>
		</relationship>
		<relationship name="encodable">
			<destination>{a4fc7b1b-313e-4c89-825b-d23ece5fbcc3}</destination>
		</relationship>
	</object>
</objects>
