<?xml version="1.0" encoding="UTF-8"?>
<objects serializationModel="Studio.02.03.00">
	<object class="ParameterPreset" id="{ac242497-af86-4329-8f6f-64819a8e40a4}">
		<property name="name">
			<value>Inside</value>
		</property>
		<relationship name="folder">
			<destination>{4a572ee9-978b-4073-8479-76b2fbac75fb}</destination>
		</relationship>
		<relationship name="parameter">
			<destination>{74cb7014-eaa3-4b2e-b5fe-eb56730c05ec}</destination>
		</relationship>
	</object>
	<object class="GameParameter" id="{74cb7014-eaa3-4b2e-b5fe-eb56730c05ec}">
		<property name="initialValue">
			<value>0</value>
		</property>
	</object>
</objects>
